rtl/gate_level_circuit.v
`timescale 1ns/1ps
module Gate_Level(clk, in, out, rstn );
input wire clk, in, rstn;
output wire out;

reg QA, QB; 
 
always@(posedge clk, negedge rstn)
begin
	if(!rstn) 	QB <= 1'b0;
	else 		QB <= in;
end

wire DA = QB & (~in);

always@(posedge clk, negedge rstn)
begin
	if(!rstn) 	QA <= 1'b0;
	else 		QA <= DA;
end

assign out = QA & in;

//endmodule
endmodule

rtl/mealy.v
`timescale 1ns/1ps
module Mealy(clk, in, out, rstn );
input wire clk, in, rstn;
output reg out;
 
reg[1:0] state;
parameter S0 = 2'd0, S1 = 2'd1, S2 = 2'd2;

always@ (posedge clk, negedge rstn)
begin
	if (!rstn)
		begin
		out <= 1'd0;
		state <= S0;	
		end
	else
		case(state)
			S0: if(in == 1'd0)
					begin 
					out <= 1'd0;
					state <= S0;
					end
				else 
					begin
					out <= 1'd0;
					state <= S1;				
					end
			S1: if(in == 1'd0)
					begin 
					out <= 1'd0;
					state <= S2;
					end
				else 
					begin
					out <= 1'd0;
					state <= S1;				
					end 
			S2: if(in == 1'd0)
					begin 
					out <= 1'd0;
					state <= S0;
					end
				else 
					begin
					out <= 1'd1;
					state <= S2;				
					end
		endcase
end 
//endmodule 
endmodule

rtl/moor.v
`timescale 1ns/1ps
module Moor(clk, in, out, rstn );
input wire clk, in, rstn;
output reg out;
 
reg[1:0] state;
parameter S0 = 2'd0, S1 = 2'd1;
parameter S2 = 2'd2, S3 = 2'd3;

always@ (posedge clk, negedge rstn)
begin
if(!rstn)
	state <= S0;
else
	case(state)
		S0: if(in == 1'd1)  state <= S1;
			else 			state <= S0;					
		S1: if(in == 1'd0)  state <= S2;
			else 			state <= S1;
		S2: if(in == 1'd1)  state <= S3;
			else 			state <= S0;
		S3: if(in == 1'd1)  state <= S0;
			else 			state <= S2;			
	endcase
end 

always@ (posedge clk, negedge rstn)
begin
	if(!rstn)
		out <= 1'b0;
	else if(state == S2) 
		out <= 1'b1;
	else
		out <= 1'b0;
end
//endmodule 
endmodule

rtl/test_bench.v
`timescale 1ns/1ps
`define CYCLE 100
module test_bench ();

//**************************** wire & reg**********************//
initial begin
    $display("//***************************************");
    $display("//==top input : clk, in, rstn");
    $display("//==top output :  out");
    $display("//***************************************");
    end
reg clk, in, rstn;
wire out;

//**************************** module **********************//
initial begin $display("===module : FSM Mealy Moor Gate_Level"); end
Moor Moor(.rstn(rstn),
			.clk(clk),
			.in(in), 
			.out(out_moor)
);

Mealy Mealy(.rstn(rstn),
			.clk(clk),
			.in(in), 
			.out(out_mealy)
);

Gate_Level Gate_Level(.rstn(rstn),
			.clk(clk),
			.in(in), 
			.out(out_gate_level)
);

//**************************** clock gen **********************//
initial begin
	$display("===starting generating clk");
	force clk = 1'b0;
	forever #(`CYCLE/2) force clk = ~clk;
	end

//**************************** initial and wavegen **********************//
initial begin
	$display("===starting dump waveform");
	$dumpfile("dump.vcd");
	$dumpvars(0,Moor);
	$dumpvars(0,Mealy);
	$dumpvars(0,Gate_Level);
	end

initial begin
    rstn = 1;
    in = 0;
    end

//**************************** main **********************//
reg [13:0]index_2;
integer index_1;
initial begin

	RESET();

	for(index_2 = 14'd0; index_2 <= 14'd500; index_2 = index_2 + 14'd7)
	begin 
        for(index_1 = 0; index_1 <= 13; index_1 = index_1 + 1)
		begin
			force in = index_2[index_1];
			if (out_moor != out_mealy) $display("Compare Error : mealy, moor");
			if (out_moor != out_gate_level ) $display("Compare Error : moor, gate_level");
			if (out_mealy != out_gate_level ) $display("Compare Error : mealy, gate_level");
			#`CYCLE;
        end
		$display("send : %d", index_2);
	end
	
	$display("===all done");
	#1000 $finish;
    end

task RESET;
begin
	force rstn = 0;
	#1_000;
	force rstn = 1;
	#1_000;
end	
endtask	
	
	
	
	
endmodule

dump.vcd
$date
	Sun Aug 26 20:54:51 2018
$end
$version
	Icarus Verilog
$end
$timescale
	1ps
$end
$scope module test_bench $end
$scope module Moor $end
$var wire 1 ! clk $end
$var wire 1 " in $end
$var wire 1 # rstn $end
$var reg 1 $ out $end
$var reg 2 % state [1:0] $end
$upscope $end
$upscope $end
$scope module test_bench $end
$scope module Mealy $end
$var wire 1 ! clk $end
$var wire 1 " in $end
$var wire 1 # rstn $end
$var reg 1 & out $end
$var reg 2 ' state [1:0] $end
$upscope $end
$upscope $end
$scope module test_bench $end
$scope module Gate_Level $end
$var wire 1 ( DA $end
$var wire 1 ! clk $end
$var wire 1 " in $end
$var wire 1 ) out $end
$var wire 1 # rstn $end
$var reg 1 * QA $end
$var reg 1 + QB $end
$upscope $end
$upscope $end
$enddefinitions $end
#0
$dumpvars
0+
0*
0)
0(
b0 '
0&
b0 %
0$
0#
0"
0!
$end
#50000
1!
#100000
0!
#150000
1!
#200000
0!
#250000
1!
#300000
0!
#350000
1!
#400000
0!
#450000
1!
#500000
0!
#550000
1!
#600000
0!
#650000
1!
#700000
0!
#750000
1!
#800000
0!
#850000
1!
#900000
0!
#950000
1!
#1000000
0!
1#
#1050000
1!
#1100000
0!
#1150000
1!
#1200000
0!
#1250000
1!
#1300000
0!
#1350000
1!
#1400000
0!
#1450000
1!
#1500000
0!
#1550000
1!
#1600000
0!
#1650000
1!
#1700000
0!
#1750000
1!
#1800000
0!
#1850000
1!
#1900000
0!
#1950000
1!
#2000000
0!
#2050000
1!
#2100000
0!
#2150000
1!
#2200000
0!
#2250000
1!
#2300000
0!
#2350000
1!
#2400000
0!
#2450000
1!
#2500000
0!
#2550000
1!
#2600000
0!
#2650000
1!
#2700000
0!
#2750000
1!
#2800000
0!
#2850000
1!
#2900000
0!
#2950000
1!
#3000000
0!
#3050000
1!
#3100000
0!
#3150000
1!
#3200000
0!
#3250000
1!
#3300000
0!
#3350000
1!
#3400000
0!
1"
#3450000
1+
b1 '
b1 %
1!
#3500000
0!
#3550000
1!
#3600000
0!
#3650000
1!
#3700000
1(
0!
0"
#3750000
0(
b10 %
b10 '
0+
1*
1!
#3800000
0!
#3850000
0*
b0 '
1$
b0 %
1!
#3900000
0!
#3950000
0$
1!
#4000000
0!
#4050000
1!
#4100000
0!
#4150000
1!
#4200000
0!
#4250000
1!
#4300000
0!
#4350000
1!
#4400000
0!
#4450000
1!
#4500000
0!
#4550000
1!
#4600000
0!
#4650000
1!
#4700000
0!
#4750000
1!
#4800000
0!
#4850000
1!
#4900000
0!
1"
#4950000
b1 %
b1 '
1+
1!
#5000000
0!
#5050000
1!
#5100000
0!
#5150000
1!
#5200000
1(
0!
0"
#5250000
0(
1*
0+
b10 '
b10 %
1!
#5300000
0!
#5350000
b0 %
1$
b0 '
0*
1!
#5400000
0!
#5450000
0$
1!
#5500000
0!
#5550000
1!
#5600000
0!
#5650000
1!
#5700000
0!
#5750000
1!
#5800000
0!
#5850000
1!
#5900000
0!
#5950000
1!
#6000000
0!
#6050000
1!
#6100000
0!
#6150000
1!
#6200000
0!
1"
#6250000
1+
b1 '
b1 %
1!
#6300000
1(
0!
0"
#6350000
0(
b10 %
b10 '
0+
1*
1!
#6400000
1)
0!
1"
#6450000
0)
0*
1+
1&
1$
b11 %
1!
#6500000
1(
0!
0"
#6550000
0(
b10 %
0$
b0 '
0&
0+
1*
1!
#6600000
1)
0!
1"
#6650000
0)
0*
1+
b1 '
1$
b11 %
1!
#6700000
1(
0!
0"
#6750000
0(
b10 %
0$
b10 '
0+
1*
1!
#6800000
0!
#6850000
0*
b0 '
1$
b0 %
1!
#6900000
0!
#6950000
0$
1!
#7000000
0!
#7050000
1!
#7100000
0!
#7150000
1!
#7200000
0!
#7250000
1!
#7300000
0!
#7350000
1!
#7400000
0!
#7450000
1!
#7500000
0!
#7550000
1!
#7600000
0!
#7650000
1!
#7700000
0!
#7750000
1!
#7800000
0!
1"
#7850000
1+
b1 '
b1 %
1!
#7900000
0!
#7950000
1!
#8000000
0!
#8050000
1!
#8100000
1(
0!
0"
#8150000
0(
b10 %
b10 '
0+
1*
1!
#8200000
0!
#8250000
0*
b0 '
1$
b0 %
1!
#8300000
0!
#8350000
0$
1!
#8400000
0!
#8450000
1!
#8500000
0!
#8550000
1!
#8600000
0!
#8650000
1!
#8700000
0!
#8750000
1!
#8800000
0!
#8850000
1!
#8900000
0!
#8950000
1!
#9000000
0!
1"
#9050000
1+
b1 '
b1 %
1!
#9100000
0!
#9150000
1!
#9200000
1(
0!
0"
#9250000
0(
1*
0+
b10 '
b10 %
1!
#9300000
0!
#9350000
b0 %
1$
b0 '
0*
1!
#9400000
0!
#9450000
0$
1!
#9500000
0!
1"
#9550000
b1 %
b1 '
1+
1!
#9600000
1(
0!
0"
#9650000
0(
1*
0+
b10 '
b10 %
1!
#9700000
0!
#9750000
b0 %
1$
b0 '
0*
1!
#9800000
0!
#9850000
0$
1!
#9900000
0!
#9950000
1!
#10000000
0!
#10050000
1!
#10100000
0!
#10150000
1!
#10200000
0!
#10250000
1!
#10300000
0!
#10350000
1!
#10400000
0!
#10450000
1!
#10500000
0!
1"
#10550000
b1 %
b1 '
1+
1!
#10600000
1(
0!
0"
#10650000
0(
1*
0+
b10 '
b10 %
1!
#10700000
1)
0!
1"
#10750000
0)
b11 %
1$
1&
1+
0*
1!
#10800000
1(
0!
0"
#10850000
0(
1*
0+
b0 '
0&
0$
b10 %
1!
#10900000
1)
0!
1"
#10950000
0)
b11 %
1$
b1 '
1+
0*
1!
#11000000
1(
0!
0"
#11050000
0(
1*
0+
b10 '
0$
b10 %
1!
#11100000
0!
#11150000
b0 %
1$
b0 '
0*
1!
#11200000
0!
#11250000
0$
1!
#11300000
0!
#11350000
1!
#11400000
0!
#11450000
1!
#11500000
0!
#11550000
1!
#11600000
0!
#11650000
1!
#11700000
0!
#11750000
1!
#11800000
0!
1"
#11850000
1+
b1 '
b1 %
1!
#11900000
1(
0!
0"
#11950000
0(
b10 %
b10 '
0+
1*
1!
#12000000
0!
#12050000
0*
b0 '
1$
b0 %
1!
#12100000
0!
#12150000
0$
1!
#12200000
0!
1"
#12250000
1+
b1 '
b1 %
1!
#12300000
0!
#12350000
1!
#12400000
1(
0!
0"
#12450000
0(
1*
0+
b10 '
b10 %
1!
#12500000
0!
#12550000
b0 %
1$
b0 '
0*
1!
#12600000
0!
#12650000
0$
1!
#12700000
0!
#12750000
1!
#12800000
0!
#12850000
1!
#12900000
0!
#12950000
1!
#13000000
0!
#13050000
1!
#13100000
0!
#13150000
1!
#13200000
0!
#13250000
1!
#13300000
0!
#13350000
1!
#13400000
0!
#13450000
1!
#13500000
0!
1"
#13550000
b1 %
b1 '
1+
1!
#13600000
0!
#13650000
1!
#13700000
0!
#13750000
1!
#13800000
1(
0!
0"
#13850000
0(
1*
0+
b10 '
b10 %
1!
#13900000
0!
#13950000
b0 %
1$
b0 '
0*
1!
#14000000
0!
#14050000
0$
1!
#14100000
0!
#14150000
1!
#14200000
0!
#14250000
1!
#14300000
0!
#14350000
1!
#14400000
0!
#14450000
1!
#14500000
0!
#14550000
1!
#14600000
0!
1"
#14650000
1+
b1 '
b1 %
1!
#14700000
0!
#14750000
1!
#14800000
0!
#14850000
1!
#14900000
0!
#14950000
1!
#15000000
0!
#15050000
1!
#15100000
0!
#15150000
1!
#15200000
1(
0!
0"
#15250000
0(
1*
0+
b10 '
b10 %
1!
#15300000
0!
#15350000
b0 %
1$
b0 '
0*
1!
#15400000
0!
#15450000
0$
1!
#15500000
0!
#15550000
1!
#15600000
0!
#15650000
1!
#15700000
0!
#15750000
1!
#15800000
0!
#15850000
1!
#15900000
0!
#15950000
1!
#16000000
0!
#16050000
1!
#16100000
0!
1"
#16150000
b1 %
b1 '
1+
1!
#16200000
0!
#16250000
1!
#16300000
1(
0!
0"
#16350000
0(
b10 %
b10 '
0+
1*
1!
#16400000
0!
#16450000
0*
b0 '
1$
b0 %
1!
#16500000
0!
#16550000
0$
1!
#16600000
0!
1"
#16650000
1+
b1 '
b1 %
1!
#16700000
1(
0!
0"
#16750000
0(
b10 %
b10 '
0+
1*
1!
#16800000
0!
#16850000
0*
b0 '
1$
b0 %
1!
#16900000
0!
#16950000
0$
1!
#17000000
0!
#17050000
1!
#17100000
0!
#17150000
1!
#17200000
0!
#17250000
1!
#17300000
0!
#17350000
1!
#17400000
0!
1"
#17450000
1+
b1 '
b1 %
1!
#17500000
1(
0!
0"
#17550000
0(
b10 %
b10 '
0+
1*
1!
#17600000
1)
0!
1"
#17650000
0)
0*
1+
1&
1$
b11 %
1!
#17700000
0!
#17750000
b0 %
0$
1!
#17800000
1(
0!
0"
#17850000
0(
1*
0+
b0 '
0&
1!
#17900000
0!
#17950000
0*
1!
#18000000
0!
1"
#18050000
1+
b1 '
b1 %
1!
#18100000
1(
0!
0"
#18150000
0(
b10 %
b10 '
0+
1*
1!
#18200000
0!
#18250000
0*
b0 '
1$
b0 %
1!
#18300000
0!
#18350000
0$
1!
#18400000
0!
#18450000
1!
#18500000
0!
#18550000
1!
#18600000
0!
#18650000
1!
#18700000
0!
#18750000
1!
#18800000
0!
#18850000
1!
#18900000
0!
#18950000
1!
#19000000
0!
1"
#19050000
1+
b1 '
b1 %
1!
#19100000
1(
0!
0"
#19150000
0(
b10 %
b10 '
0+
1*
1!
#19200000
1)
0!
1"
#19250000
0)
0*
1+
1&
1$
b11 %
1!
#19300000
1(
0!
0"
#19350000
0(
b10 %
0$
b0 '
0&
0+
1*
1!
#19400000
1)
0!
1"
#19450000
0)
0*
1+
b1 '
1$
b11 %
1!
#19500000
1(
0!
0"
#19550000
0(
b10 %
0$
b10 '
0+
1*
1!
#19600000
0!
#19650000
0*
b0 '
1$
b0 %
1!
#19700000
0!
#19750000
0$
1!
#19800000
0!
#19850000
1!
#19900000
0!
#19950000
1!
#20000000
0!
#20050000
1!
#20100000
0!
#20150000
1!
#20200000
0!
1"
#20250000
1+
b1 '
b1 %
1!
#20300000
0!
#20350000
1!
#20400000
1(
0!
0"
#20450000
0(
1*
0+
b10 '
b10 %
1!
#20500000
1)
0!
1"
#20550000
0)
b11 %
1$
1&
1+
0*
1!
#20600000
0!
#20650000
0$
b0 %
1!
#20700000
1(
0!
0"
#20750000
0(
b0 '
0&
0+
1*
1!
#20800000
1)
0!
1"
#20850000
0)
0*
1+
b1 '
b1 %
1!
#20900000
1(
0!
0"
#20950000
0(
b10 %
b10 '
0+
1*
1!
#21000000
0!
#21050000
0*
b0 '
1$
b0 %
1!
#21100000
0!
#21150000
0$
1!
#21200000
0!
#21250000
1!
#21300000
0!
#21350000
1!
#21400000
0!
#21450000
1!
#21500000
0!
#21550000
1!
#21600000
0!
#21650000
1!
#21700000
0!
1"
#21750000
b1 %
b1 '
1+
1!
#21800000
1(
0!
0"
#21850000
0(
1*
0+
b10 '
b10 %
1!
#21900000
0!
#21950000
b0 %
1$
b0 '
0*
1!
#22000000
0!
#22050000
0$
1!
#22100000
0!
1"
#22150000
b1 %
b1 '
1+
1!
#22200000
0!
#22250000
1!
#22300000
1(
0!
0"
#22350000
0(
b10 %
b10 '
0+
1*
1!
#22400000
0!
#22450000
0*
b0 '
1$
b0 %
1!
#22500000
0!
#22550000
0$
1!
#22600000
0!
#22650000
1!
#22700000
0!
#22750000
1!
#22800000
0!
#22850000
1!
#22900000
0!
#22950000
1!
#23000000
0!
1"
#23050000
1+
b1 '
b1 %
1!
#23100000
1(
0!
0"
#23150000
0(
b10 %
b10 '
0+
1*
1!
#23200000
0!
#23250000
0*
b0 '
1$
b0 %
1!
#23300000
0!
1"
#23350000
b1 %
0$
b1 '
1+
1!
#23400000
1(
0!
0"
#23450000
0(
1*
0+
b10 '
b10 %
1!
#23500000
1)
0!
1"
#23550000
0)
b11 %
1$
1&
1+
0*
1!
#23600000
0!
#23650000
0$
b0 %
1!
#23700000
1(
0!
0"
#23750000
0(
b0 '
0&
0+
1*
1!
#23800000
0!
#23850000
0*
1!
#23900000
0!
#23950000
1!
#24000000
0!
#24050000
1!
#24100000
0!
#24150000
1!
#24200000
0!
#24250000
1!
#24300000
0!
#24350000
1!
#24400000
0!
#24450000
1!
#24500000
0!
#24550000
1!
#24600000
0!
#24650000
1!
#24700000
0!
#24750000
1!
#24800000
0!
1"
#24850000
1+
b1 '
b1 %
1!
#24900000
0!
#24950000
1!
#25000000
0!
#25050000
1!
#25100000
1(
0!
0"
#25150000
0(
b10 %
b10 '
0+
1*
1!
#25200000
0!
#25250000
0*
b0 '
1$
b0 %
1!
#25300000
0!
#25350000
0$
1!
#25400000
0!
#25450000
1!
#25500000
0!
#25550000
1!
#25600000
0!
#25650000
1!
#25700000
0!
#25750000
1!
#25800000
0!
1"
#25850000
1+
b1 '
b1 %
1!
#25900000
0!
#25950000
1!
#26000000
0!
#26050000
1!
#26100000
1(
0!
0"
#26150000
0(
b10 %
b10 '
0+
1*
1!
#26200000
1)
0!
1"
#26250000
0)
0*
1+
1&
1$
b11 %
1!
#26300000
0!
#26350000
b0 %
0$
1!
#26400000
0!
#26450000
b1 %
1!
#26500000
1(
0!
0"
#26550000
0(
b10 %
b0 '
0&
0+
1*
1!
#26600000
0!
#26650000
0*
1$
b0 %
1!
#26700000
0!
#26750000
0$
1!
#26800000
0!
#26850000
1!
#26900000
0!
#26950000
1!
#27000000
0!
#27050000
1!
#27100000
0!
#27150000
1!
#27200000
0!
#27250000
1!
#27300000
0!
1"
#27350000
b1 %
b1 '
1+
1!
#27400000
0!
#27450000
1!
#27500000
0!
#27550000
1!
#27600000
0!
#27650000
1!
#27700000
0!
#27750000
1!
#27800000
0!
#27850000
1!
#27900000
1(
0!
0"
#27950000
0(
b10 %
b10 '
0+
1*
1!
#28000000
0!
#28050000
0*
b0 '
1$
b0 %
1!
#28100000
0!
#28150000
0$
1!
#28200000
0!
#28250000
1!
#28300000
0!
#28350000
1!
#28400000
0!
#28450000
1!
#28500000
0!
#28550000
1!
#28600000
0!
1"
#28650000
1+
b1 '
b1 %
1!
#28700000
1(
0!
0"
#28750000
0(
b10 %
b10 '
0+
1*
1!
#28800000
1)
0!
1"
#28850000
0)
0*
1+
1&
1$
b11 %
1!
#28900000
1(
0!
0"
#28950000
0(
b10 %
0$
b0 '
0&
0+
1*
1!
#29000000
0!
#29050000
0*
1$
b0 %
1!
#29100000
0!
#29150000
0$
1!
#29200000
0!
#29250000
1!
#29300000
0!
1"
#29350000
b1 %
b1 '
1+
1!
#29400000
1(
0!
0"
#29450000
0(
1*
0+
b10 '
b10 %
1!
#29500000
0!
#29550000
b0 %
1$
b0 '
0*
1!
#29600000
0!
#29650000
0$
1!
#29700000
0!
#29750000
1!
#29800000
0!
#29850000
1!
#29900000
0!
#29950000
1!
#30000000
0!
#30050000
1!
#30100000
0!
#30150000
1!
#30200000
0!
1"
#30250000
1+
b1 '
b1 %
1!
#30300000
0!
#30350000
1!
#30400000
1(
0!
0"
#30450000
0(
1*
0+
b10 '
b10 %
1!
#30500000
0!
#30550000
b0 %
1$
b0 '
0*
1!
#30600000
0!
#30650000
0$
1!
#30700000
0!
1"
#30750000
b1 %
b1 '
1+
1!
#30800000
1(
0!
0"
#30850000
0(
1*
0+
b10 '
b10 %
1!
#30900000
0!
#30950000
b0 %
1$
b0 '
0*
1!
#31000000
0!
#31050000
0$
1!
#31100000
0!
#31150000
1!
#31200000
0!
#31250000
1!
#31300000
0!
#31350000
1!
#31400000
0!
1"
#31450000
1+
b1 '
b1 %
1!
#31500000
0!
#31550000
1!
#31600000
1(
0!
0"
#31650000
0(
1*
0+
b10 '
b10 %
1!
#31700000
0!
#31750000
b0 %
1$
b0 '
0*
1!
#31800000
0!
1"
#31850000
1+
b1 '
0$
b1 %
1!
#31900000
1(
0!
0"
#31950000
0(
b10 %
b10 '
0+
1*
1!
#32000000
0!
#32050000
0*
b0 '
1$
b0 %
1!
#32100000
0!
1"
#32150000
b1 %
0$
b1 '
1+
1!
#32200000
1(
0!
0"
#32250000
0(
1*
0+
b10 '
b10 %
1!
#32300000
0!
#32350000
b0 %
1$
b0 '
0*
1!
#32400000
0!
#32450000
0$
1!
#32500000
0!
#32550000
1!
#32600000
0!
#32650000
1!
#32700000
0!
#32750000
1!
#32800000
0!
#32850000
1!
#32900000
0!
1"
#32950000
b1 %
b1 '
1+
1!
#33000000
1(
0!
0"
#33050000
0(
1*
0+
b10 '
b10 %
1!
#33100000
1)
0!
1"
#33150000
0)
b11 %
1$
1&
1+
0*
1!
#33200000
0!
#33250000
0$
b0 %
1!
#33300000
1(
0!
0"
#33350000
0(
b0 '
0&
0+
1*
1!
#33400000
0!
#33450000
0*
1!
#33500000
0!
1"
#33550000
b1 %
b1 '
1+
1!
#33600000
1(
0!
0"
#33650000
0(
1*
0+
b10 '
b10 %
1!
#33700000
0!
#33750000
b0 %
1$
b0 '
0*
1!
#33800000
0!
#33850000
0$
1!
#33900000
0!
#33950000
1!
#34000000
0!
#34050000
1!
#34100000
0!
#34150000
1!
#34200000
0!
1"
#34250000
1+
b1 '
b1 %
1!
#34300000
1(
0!
0"
#34350000
0(
b10 %
b10 '
0+
1*
1!
#34400000
0!
#34450000
0*
b0 '
1$
b0 %
1!
#34500000
0!
#34550000
0$
1!
#34600000
0!
#34650000
1!
#34700000
0!
1"
#34750000
b1 %
b1 '
1+
1!
#34800000
1(
0!
0"
#34850000
0(
1*
0+
b10 '
b10 %
1!
#34900000
1)
0!
1"
#34950000
0)
b11 %
1$
1&
1+
0*
1!
#35000000
1(
0!
0"
#35050000
0(
1*
0+
b0 '
0&
0$
b10 %
1!
#35100000
0!
#35150000
b0 %
1$
0*
1!
#35200000
0!
#35250000
0$
1!
#35300000
0!
#35350000
1!
#35400000
0!
#35450000
1!
#35500000
0!
#35550000
1!
#35600000
0!
#35650000
1!
#35700000
0!
#35750000
1!
#35800000
0!
#35850000
1!
#35900000
0!
1"
#35950000
b1 %
b1 '
1+
1!
#36000000
1(
0!
0"
#36050000
0(
1*
0+
b10 '
b10 %
1!
#36100000
1)
0!
1"
#36150000
0)
b11 %
1$
1&
1+
0*
1!
#36200000
1(
0!
0"
#36250000
0(
1*
0+
b0 '
0&
0$
b10 %
1!
#36300000
1)
0!
1"
#36350000
0)
b11 %
1$
b1 '
1+
0*
1!
#36400000
1(
0!
0"
#36450000
0(
1*
0+
b10 '
0$
b10 %
1!
#36500000
0!
#36550000
b0 %
1$
b0 '
0*
1!
#36600000
0!
#36650000
0$
1!
#36700000
0!
#36750000
1!
#36800000
0!
#36850000
1!
#36900000
0!
#36950000
1!
#37000000
0!
1"
#37050000
1+
b1 '
b1 %
1!
#37100000
0!
#37150000
1!
#37200000
0!
#37250000
1!
#37300000
0!
#37350000
1!
#37400000
1(
0!
0"
#37450000
0(
1*
0+
b10 '
b10 %
1!
#37500000
1)
0!
1"
#37550000
0)
b11 %
1$
1&
1+
0*
1!
#37600000
1(
0!
0"
#37650000
0(
1*
0+
b0 '
0&
0$
b10 %
1!
#37700000
1)
0!
1"
#37750000
0)
b11 %
1$
b1 '
1+
0*
1!
#37800000
1(
0!
0"
#37850000
0(
1*
0+
b10 '
0$
b10 %
1!
#37900000
0!
#37950000
b0 %
1$
b0 '
0*
1!
#38000000
0!
#38050000
0$
1!
#38100000
0!
#38150000
1!
#38200000
0!
#38250000
1!
#38300000
0!
#38350000
1!
#38400000
0!
#38450000
1!
#38500000
0!
1"
#38550000
b1 %
b1 '
1+
1!
#38600000
0!
#38650000
1!
#38700000
1(
0!
0"
#38750000
0(
b10 %
b10 '
0+
1*
1!
#38800000
1)
0!
1"
#38850000
0)
0*
1+
1&
1$
b11 %
1!
#38900000
0!
#38950000
b0 %
0$
1!
#39000000
1(
0!
0"
#39050000
0(
1*
0+
b0 '
0&
1!
#39100000
1)
0!
1"
#39150000
0)
b1 %
b1 '
1+
0*
1!
#39200000
1(
0!
0"
#39250000
0(
1*
0+
b10 '
b10 %
1!
#39300000
0!
#39350000
b0 %
1$
b0 '
0*
1!
#39400000
0!
#39450000
0$
1!
#39500000
0!
#39550000
1!
#39600000
0!
#39650000
1!
#39700000
0!
#39750000
1!
#39800000
0!
1"
#39850000
1+
b1 '
b1 %
1!
#39900000
1(
0!
0"
#39950000
0(
b10 %
b10 '
0+
1*
1!
#40000000
1)
0!
1"
#40050000
0)
0*
1+
1&
1$
b11 %
1!
#40100000
0!
#40150000
b0 %
0$
1!
#40200000
0!
#40250000
b1 %
1!
#40300000
0!
#40350000
1!
#40400000
1(
0!
0"
#40450000
0(
1*
0+
b0 '
0&
b10 %
1!
#40500000
1)
0!
1"
#40550000
0)
b11 %
1$
b1 '
1+
0*
1!
#40600000
1(
0!
0"
#40650000
0(
1*
0+
b10 '
0$
b10 %
1!
#40700000
0!
#40750000
b0 %
1$
b0 '
0*
1!
#40800000
0!
#40850000
0$
1!
#40900000
0!
#40950000
1!
#41000000
0!
#41050000
1!
#41100000
0!
#41150000
1!
#41200000
0!
#41250000
1!
#41300000
0!
#41350000
1!
#41400000
0!
1"
#41450000
1+
b1 '
b1 %
1!
#41500000
1(
0!
0"
#41550000
0(
b10 %
b10 '
0+
1*
1!
#41600000
0!
#41650000
0*
b0 '
1$
b0 %
1!
#41700000
0!
#41750000
0$
1!
#41800000
0!
1"
#41850000
1+
b1 '
b1 %
1!
#41900000
0!
#41950000
1!
#42000000
1(
0!
0"
#42050000
0(
1*
0+
b10 '
b10 %
1!
#42100000
0!
#42150000
b0 %
1$
b0 '
0*
1!
#42200000
0!
#42250000
0$
1!
#42300000
0!
#42350000
1!
#42400000
0!
#42450000
1!
#42500000
0!
#42550000
1!
#42600000
0!
1"
#42650000
1+
b1 '
b1 %
1!
#42700000
0!
#42750000
1!
#42800000
1(
0!
0"
#42850000
0(
1*
0+
b10 '
b10 %
1!
#42900000
1)
0!
1"
#42950000
0)
b11 %
1$
1&
1+
0*
1!
#43000000
1(
0!
0"
#43050000
0(
1*
0+
b0 '
0&
0$
b10 %
1!
#43100000
0!
#43150000
b0 %
1$
0*
1!
#43200000
0!
1"
#43250000
1+
b1 '
0$
b1 %
1!
#43300000
0!
#43350000
1!
#43400000
1(
0!
0"
#43450000
0(
1*
0+
b10 '
b10 %
1!
#43500000
0!
#43550000
b0 %
1$
b0 '
0*
1!
#43600000
0!
#43650000
0$
1!
#43700000
0!
#43750000
1!
#43800000
0!
#43850000
1!
#43900000
0!
#43950000
1!
#44000000
0!
#44050000
1!
#44100000
0!
1"
#44150000
b1 %
b1 '
1+
1!
#44200000
1(
0!
0"
#44250000
0(
1*
0+
b10 '
b10 %
1!
#44300000
0!
#44350000
b0 %
1$
b0 '
0*
1!
#44400000
0!
1"
#44450000
1+
b1 '
0$
b1 %
1!
#44500000
1(
0!
0"
#44550000
0(
b10 %
b10 '
0+
1*
1!
#44600000
1)
0!
1"
#44650000
0)
0*
1+
1&
1$
b11 %
1!
#44700000
0!
#44750000
b0 %
0$
1!
#44800000
1(
0!
0"
#44850000
0(
1*
0+
b0 '
0&
1!
#44900000
0!
#44950000
0*
1!
#45000000
0!
#45050000
1!
#45100000
0!
#45150000
1!
#45200000
0!
#45250000
1!
#45300000
0!
#45350000
1!
#45400000
0!
1"
#45450000
1+
b1 '
b1 %
1!
#45500000
1(
0!
0"
#45550000
0(
b10 %
b10 '
0+
1*
1!
#45600000
0!
#45650000
0*
b0 '
1$
b0 %
1!
#45700000
0!
1"
#45750000
b1 %
0$
b1 '
1+
1!
#45800000
0!
#45850000
1!
#45900000
1(
0!
0"
#45950000
0(
b10 %
b10 '
0+
1*
1!
#46000000
1)
0!
1"
#46050000
0)
0*
1+
1&
1$
b11 %
1!
#46100000
0!
#46150000
b0 %
0$
1!
#46200000
1(
0!
0"
#46250000
0(
1*
0+
b0 '
0&
1!
#46300000
0!
#46350000
0*
1!
#46400000
0!
#46450000
1!
#46500000
0!
#46550000
1!
#46600000
0!
#46650000
1!
#46700000
0!
#46750000
1!
#46800000
0!
#46850000
1!
#46900000
0!
#46950000
1!
#47000000
0!
#47050000
1!
#47100000
0!
#47150000
1!
#47200000
0!
#47250000
1!
#47300000
0!
1"
#47350000
b1 %
b1 '
1+
1!
#47400000
0!
#47450000
1!
#47500000
0!
#47550000
1!
#47600000
1(
0!
0"
#47650000
0(
1*
0+
b10 '
b10 %
1!
#47700000
0!
#47750000
b0 %
1$
b0 '
0*
1!
#47800000
0!
#47850000
0$
1!
#47900000
0!
#47950000
1!
#48000000
0!
#48050000
1!
#48100000
0!
#48150000
1!
#48200000
0!
1"
#48250000
1+
b1 '
b1 %
1!
#48300000
0!
#48350000
1!
#48400000
0!
#48450000
1!
#48500000
1(
0!
0"
#48550000
0(
b10 %
b10 '
0+
1*
1!
#48600000
0!
#48650000
0*
b0 '
1$
b0 %
1!
#48700000
0!
1"
#48750000
b1 %
0$
b1 '
1+
1!
#48800000
0!
#48850000
1!
#48900000
0!
#48950000
1!
#49000000
1(
0!
0"
#49050000
0(
1*
0+
b10 '
b10 %
1!
#49100000
0!
#49150000
b0 %
1$
b0 '
0*
1!
#49200000
0!
#49250000
0$
1!
#49300000
0!
#49350000
1!
#49400000
0!
#49450000
1!
#49500000
0!
#49550000
1!
#49600000
0!
#49650000
1!
#49700000
0!
1"
#49750000
b1 %
b1 '
1+
1!
#49800000
0!
#49850000
1!
#49900000
0!
#49950000
1!
#50000000
1(
0!
0"
#50050000
0(
1*
0+
b10 '
b10 %
1!
#50100000
1)
0!
1"
#50150000
0)
b11 %
1$
1&
1+
0*
1!
#50200000
0!
#50250000
0$
b0 %
1!
#50300000
0!
#50350000
b1 %
1!
#50400000
1(
0!
0"
#50450000
0(
1*
0+
b0 '
0&
b10 %
1!
#50500000
0!
#50550000
b0 %
1$
0*
1!
#50600000
0!
#50650000
0$
1!
#50700000
0!
#50750000
1!
#50800000
0!
#50850000
1!
#50900000
0!
#50950000
1!
#51000000
0!
1"
#51050000
1+
b1 '
b1 %
1!
