rtl/gate_level_circuit.v
`timescale 1ns/1ps
module Gate_Level(clk, in, out, rstn, sync_out );
input wire clk, in, rstn;
output reg  sync_out;
output wire out;

reg QA, QB; 
 
wire DB = in & (~QB); 
 
always@(posedge clk, negedge rstn)
begin
	if(!rstn) 	QB <= 1'b0;
	else 		QB <= DB;
end

wire DA = (QA & in & (~QB)) | (QB & (~in));

always@(posedge clk, negedge rstn)
begin
	if(!rstn) 	QA <= 1'b0;
	else 		QA <= DA;
end

assign out = QA & in & (~QB);

//synchronous mealy FSM
always@(posedge clk, negedge rstn)
begin
	if(!rstn) 	sync_out <= 1'b0;
	else 		sync_out <= out;
end


//endmodule
endmodule

rtl/mealy.v
`timescale 1ns/1ps
module Mealy(clk, in, out, rstn, sync_out );
input wire clk, in, rstn;
output reg out, sync_out;
  
reg [1:0]  state;
reg [1:0]  next_state;
parameter S0 = 2'd0, S1 = 2'd1;
parameter S2 = 2'd2, S3 = 2'd3;

always@ (posedge clk, negedge rstn)
begin
	if(!rstn)
		state <= S0;
	else
		state <= next_state;
end

always@(*)
begin
	case(state)
		S0: if(in == 1'd1)  next_state = S1;
			else 			next_state = S0;					
		S1: if(in == 1'd0)  next_state = S2;
			else 			next_state = S0;
		S2: if(in == 1'd1)  next_state = S3;
			else 			next_state = S0;
		S3: if(in == 1'd1)  next_state = S0;
			else 			next_state = S2;		
		default : 			next_state = S0;
	endcase
end

always@(*)
begin
	case(state)
		S0: if(in == 1'd1)  out = 1'd0;
			else 			out = 1'd0;					
		S1: if(in == 1'd0)  out = 1'd0;
			else 			out = 1'd0;
		S2: if(in == 1'd1)  out = 1'd1;
			else 			out = 1'd0;
		S3: if(in == 1'd1)  out = 1'd0;
			else 			out = 1'd0;		
		default : 			out = 1'd0;
	endcase
end

//synchronous mealy FSM
always@ (posedge clk, negedge rstn)
begin
	if(!rstn)
		sync_out <= 1'b0;
	else
		sync_out <= out;
end

//endmodule 
endmodule

rtl/moor.v
`timescale 1ns/1ps
module Moor(clk, in, out, rstn );
input wire clk, in, rstn;
output reg out;
 
reg [1:0]  state;
reg [1:0]  next_state;
parameter S0 = 2'd0, S1 = 2'd1;
parameter S2 = 2'd2, S3 = 2'd3;

always@ (posedge clk, negedge rstn)
begin
	if(!rstn)
		state <= S0;
	else
		state <= next_state;
end

always@(*)
begin
	case(state)
		S0: if(in == 1'd1)  next_state = S1;
			else 			next_state = S0;					
		S1: if(in == 1'd0)  next_state = S2;
			else 			next_state = S0;
		S2: if(in == 1'd1)  next_state = S3;
			else 			next_state = S0;
		S3: if(in == 1'd1)  next_state = S0;
			else 			next_state = S2;		
		default : 			next_state = S0;
	endcase
end

always@(*)
begin
	case(state)
		S0:   	  out = 0;
		S1:   	  out = 0;
		S2:		  out = 0;
		S3:		  out = 1;
		default : out = 0;
	endcase
end
//endmodule 
endmodule

rtl/top_digital.v
`timescale 1ns/1ps

module top_digital(clk, in, rstn,
					out_moor, out_mealy, sync_mealy_out,
					out_gate_level, sync_out_gate_level);
					
input wire clk, in, rstn; 
output wire out_moor;
output wire out_mealy, sync_mealy_out;
output wire out_gate_level, sync_out_gate_level;

Moor Moor(.rstn(rstn),
			.clk(clk),
			.in(in), 
			.out(out_moor)
);

Mealy Mealy(.rstn(rstn),
			.clk(clk),
			.in(in), 
			.out(out_mealy),
			.sync_out(sync_mealy_out)
);

Gate_Level Gate_Level(.rstn(rstn),
			.clk(clk),
			.in(in), 
			.out(out_gate_level),
			.sync_out(sync_out_gate_level)
);
 
endmodule

rtl/test_bench.v
`timescale 1ns/1ps
`define CYCLE 100
module test_bench ();

//**************************** wire & reg**********************//
initial begin
    $display("//***************************************");
    $display("//==top input : clk, in, rstn");
    $display("//==top output :  out, sync_out");
    $display("//***************************************");
    end
reg clk, in, rstn;
wire out_moor;
wire out_mealy, sync_mealy_out;
wire out_gate_level, sync_out_gate_level;

//**************************** module **********************//
initial begin $display("===module : FSM Mealy Moor Gate_Level"); end
//number of moor state = number of mealy state * number of output +1

//Mealy Machines tend to have less states
// Different outputs on arcs (n^2) rather than states (n)
// Moore Machines are safer to use
// Outputs change at clock edge (always one cycle later)
// In Mealy machines, input change can cause output change as soon as
//logic is done – a big problem when two machines are interconnected –
//asynchronous feedback
// Mealy Machines react faster to inputs
// React in same cycle – don't need to wait for clock
// In Moore machines, more logic may be necessary to decode state
//into outputs – more gate delays after

// small fsm -> binary, gray code; big fsm -> one hot

top_digital top_digital(.rstn(rstn),
						.clk(clk),
						.in(in), 
						.out_moor(out_moor),
						.out_mealy(out_mealy),
						.sync_mealy_out(sync_mealy_out),					
						.out_gate_level(out_gate_level),
						.sync_out_gate_level(sync_out_gate_level)					
					);


//**************************** clock gen **********************//
initial begin
	$display("===starting generating clk");
	force clk = 1'b0;
	forever #(`CYCLE/2) force clk = ~clk;
	end

//**************************** initial and wavegen **********************//
initial begin
	$display("===starting dump waveform");
	$dumpfile("dump.vcd");
	$dumpvars(0,top_digital);
	end

initial begin
    rstn = 1;
    in = 0;
    end

//**************************** main **********************//
reg [13:0]index_2;
integer index_1;
initial begin

	RESET();

	for(index_2 = 14'd0; index_2 <= 14'd500; index_2 = index_2 + 14'd1)
	begin 
        for(index_1 = 0; index_1 <= 13; index_1 = index_1 + 1)
		begin
			force in = index_2[index_1];
			if (out_moor != sync_mealy_out) 
				$display("Compare Error : mealy, moor @ %t,", $time);
			else if (out_moor != sync_out_gate_level ) 
				$display("Compare Error : moor, gate_level @ %t,", $time);
			else if (sync_mealy_out != sync_out_gate_level ) 
				$display("Compare Error : mealy, gate_level @ %t,", $time);
			//else $display("Compare OK");
			#`CYCLE;
        end
		
		if (index_2%14'd64 == 0)
		begin 
		$display("send : 0x%h, the time is %t", index_2, $time); 
		end
	end
	
	$display("===all done");
	#1000 $finish;
    end

task RESET;
begin
	force rstn = 0;
	#1_000;
	force rstn = 1;
	#1_000;
end	
endtask	
	
	
	
	
endmodule

dump.vcd
$date
	Mon Nov 26 21:10:04 2018
$end
$version
	Icarus Verilog
$end
$timescale
	1ps
$end
$scope module test_bench $end
$scope module top_digital $end
$var wire 1 ! clk $end
$var wire 1 " in $end
$var wire 1 # rstn $end
$var wire 1 $ sync_out_gate_level $end
$var wire 1 % sync_mealy_out $end
$var wire 1 & out_moor $end
$var wire 1 ' out_mealy $end
$var wire 1 ( out_gate_level $end
$scope module Gate_Level $end
$var wire 1 ) DA $end
$var wire 1 * DB $end
$var wire 1 ! clk $end
$var wire 1 " in $end
$var wire 1 ( out $end
$var wire 1 # rstn $end
$var reg 1 + QA $end
$var reg 1 , QB $end
$var reg 1 $ sync_out $end
$upscope $end
$scope module Mealy $end
$var wire 1 ! clk $end
$var wire 1 " in $end
$var wire 1 # rstn $end
$var reg 2 - next_state [1:0] $end
$var reg 1 ' out $end
$var reg 2 . state [1:0] $end
$var reg 1 % sync_out $end
$upscope $end
$scope module Moor $end
$var wire 1 ! clk $end
$var wire 1 " in $end
$var wire 1 # rstn $end
$var reg 2 / next_state [1:0] $end
$var reg 1 & out $end
$var reg 2 0 state [1:0] $end
$upscope $end
$upscope $end
$upscope $end
$enddefinitions $end
#0
$dumpvars
b0 0
b0 /
b0 .
b0 -
0,
0+
0*
0)
0(
0'
0&
0%
0$
0#
0"
0!
$end
#50000
1!
#100000
0!
#150000
1!
#200000
0!
#250000
1!
#300000
0!
#350000
1!
#400000
0!
#450000
1!
#500000
0!
#550000
1!
#600000
0!
#650000
1!
#700000
0!
#750000
1!
#800000
0!
#850000
1!
#900000
0!
#950000
1!
#1000000
0!
1#
#1050000
1!
#1100000
0!
#1150000
1!
#1200000
0!
#1250000
1!
#1300000
0!
#1350000
1!
#1400000
0!
#1450000
1!
#1500000
0!
#1550000
1!
#1600000
0!
#1650000
1!
#1700000
0!
#1750000
1!
#1800000
0!
#1850000
1!
#1900000
0!
#1950000
1!
#2000000
0!
0"
#2050000
1!
#2100000
0!
0"
#2150000
1!
#2200000
0!
0"
#2250000
1!
#2300000
0!
0"
#2350000
1!
#2400000
0!
0"
#2450000
1!
#2500000
0!
0"
#2550000
1!
#2600000
0!
0"
#2650000
1!
#2700000
0!
0"
#2750000
1!
#2800000
0!
0"
#2850000
1!
#2900000
0!
0"
#2950000
1!
#3000000
0!
0"
#3050000
1!
#3100000
0!
0"
#3150000
1!
#3200000
0!
0"
#3250000
1!
#3300000
0!
0"
#3350000
1!
#3400000
1*
b1 -
b1 /
0!
1"
#3450000
0*
b0 -
b0 /
1,
b1 .
b1 0
1!
#3500000
1)
b10 -
b10 /
0!
0"
#3550000
0)
b0 /
b0 -
b10 0
b10 .
0,
1+
1!
#3600000
0!
0"
#3650000
0+
b0 .
b0 0
1!
#3700000
0!
0"
#3750000
1!
#3800000
0!
0"
#3850000
1!
#3900000
0!
0"
#3950000
1!
#4000000
0!
0"
#4050000
1!
#4100000
0!
0"
#4150000
1!
#4200000
0!
0"
#4250000
1!
#4300000
0!
0"
#4350000
1!
#4400000
0!
0"
#4450000
1!
#4500000
0!
0"
#4550000
1!
#4600000
0!
0"
#4650000
1!
#4700000
0!
0"
#4750000
1!
#4800000
0!
0"
#4850000
1!
#4900000
1*
b1 -
b1 /
0!
1"
#4950000
0*
b0 /
b0 -
b1 0
b1 .
1,
1!
#5000000
1)
b10 -
b10 /
0!
0"
#5050000
0)
b0 -
b0 /
1+
0,
b10 .
b10 0
1!
#5100000
0!
0"
#5150000
b0 0
b0 .
0+
1!
#5200000
0!
0"
#5250000
1!
#5300000
0!
0"
#5350000
1!
#5400000
0!
0"
#5450000
1!
#5500000
0!
0"
#5550000
1!
#5600000
0!
0"
#5650000
1!
#5700000
0!
0"
#5750000
1!
#5800000
0!
0"
#5850000
1!
#5900000
0!
0"
#5950000
1!
#6000000
0!
0"
#6050000
1!
#6100000
0!
0"
#6150000
1!
#6200000
1*
b1 -
b1 /
0!
1"
#6250000
0*
b0 -
b0 /
1,
b1 .
b1 0
1!
#6300000
0!
1"
#6350000
1*
b1 /
b1 -
b0 0
b0 .
0,
1!
#6400000
0*
b0 -
b0 /
0!
0"
#6450000
1!
#6500000
0!
0"
#6550000
1!
#6600000
0!
0"
#6650000
1!
#6700000
0!
0"
#6750000
1!
#6800000
0!
0"
#6850000
1!
#6900000
0!
0"
#6950000
1!
#7000000
0!
0"
#7050000
1!
#7100000
0!
0"
#7150000
1!
#7200000
0!
0"
#7250000
1!
#7300000
0!
0"
#7350000
1!
#7400000
0!
0"
#7450000
1!
#7500000
0!
0"
#7550000
1!
#7600000
0!
0"
#7650000
1!
#7700000
0!
0"
#7750000
1!
#7800000
1*
b1 -
b1 /
0!
1"
#7850000
0*
b0 -
b0 /
1,
b1 .
b1 0
1!
#7900000
1)
b10 -
b10 /
0!
0"
#7950000
0)
b0 /
b0 -
b10 0
b10 .
0,
1+
1!
#8000000
0!
0"
#8050000
0+
b0 .
b0 0
1!
#8100000
0!
0"
#8150000
1!
#8200000
0!
0"
#8250000
1!
#8300000
0!
0"
#8350000
1!
#8400000
0!
0"
#8450000
1!
#8500000
0!
0"
#8550000
1!
#8600000
0!
0"
#8650000
1!
#8700000
0!
0"
#8750000
1!
#8800000
0!
0"
#8850000
1!
#8900000
0!
0"
#8950000
1!
#9000000
1*
b1 -
b1 /
0!
1"
#9050000
0*
b0 -
b0 /
1,
b1 .
b1 0
1!
#9100000
1)
b10 -
b10 /
0!
0"
#9150000
0)
b0 /
b0 -
b10 0
b10 .
0,
1+
1!
#9200000
1)
1(
1*
b11 -
1'
b11 /
0!
1"
#9250000
0)
0(
0*
0'
b0 -
1&
b0 /
1$
1,
1%
b11 .
b11 0
1!
#9300000
1)
b10 -
b10 /
0!
0"
#9350000
0)
0&
b0 /
b0 -
b10 0
b10 .
0%
0,
0$
1!
#9400000
0!
0"
#9450000
0+
b0 .
b0 0
1!
#9500000
0!
0"
#9550000
1!
#9600000
0!
0"
#9650000
1!
#9700000
0!
0"
#9750000
1!
#9800000
0!
0"
#9850000
1!
#9900000
0!
0"
#9950000
1!
#10000000
0!
0"
#10050000
1!
#10100000
0!
0"
#10150000
1!
#10200000
0!
0"
#10250000
1!
#10300000
0!
0"
#10350000
1!
#10400000
0!
0"
#10450000
1!
#10500000
1*
b1 -
b1 /
0!
1"
#10550000
0*
b0 /
b0 -
b1 0
b1 .
1,
1!
#10600000
0!
1"
#10650000
1*
b1 -
b1 /
0,
b0 .
b0 0
1!
#10700000
0*
b0 -
b0 /
0!
0"
#10750000
1!
#10800000
0!
0"
#10850000
1!
#10900000
0!
0"
#10950000
1!
#11000000
0!
0"
#11050000
1!
#11100000
0!
0"
#11150000
1!
#11200000
0!
0"
#11250000
1!
#11300000
0!
0"
#11350000
1!
#11400000
0!
0"
#11450000
1!
#11500000
0!
0"
#11550000
1!
#11600000
0!
0"
#11650000
1!
#11700000
0!
0"
#11750000
1!
#11800000
1*
b1 -
b1 /
0!
1"
#11850000
0*
b0 -
b0 /
1,
b1 .
b1 0
1!
#11900000
0!
1"
#11950000
1*
b1 /
b1 -
b0 0
b0 .
0,
1!
#12000000
0!
1"
#12050000
0*
b0 -
b0 /
1,
b1 .
b1 0
1!
#12100000
1)
b10 -
b10 /
0!
0"
#12150000
0)
b0 /
b0 -
b10 0
b10 .
0,
1+
1!
#12200000
0!
0"
#12250000
0+
b0 .
b0 0
1!
#12300000
0!
0"
#12350000
1!
#12400000
0!
0"
#12450000
1!
#12500000
0!
0"
#12550000
1!
#12600000
0!
0"
#12650000
1!
#12700000
0!
0"
#12750000
1!
#12800000
0!
0"
#12850000
1!
#12900000
0!
0"
#12950000
1!
#13000000
0!
0"
#13050000
1!
#13100000
0!
0"
#13150000
1!
#13200000
0!
0"
#13250000
1!
#13300000
0!
0"
#13350000
1!
#13400000
0!
0"
#13450000
1!
#13500000
1*
b1 -
b1 /
0!
1"
#13550000
0*
b0 /
b0 -
b1 0
b1 .
1,
1!
#13600000
1)
b10 -
b10 /
0!
0"
#13650000
0)
b0 -
b0 /
1+
0,
b10 .
b10 0
1!
#13700000
0!
0"
#13750000
b0 0
b0 .
0+
1!
#13800000
0!
0"
#13850000
1!
#13900000
0!
0"
#13950000
1!
#14000000
0!
0"
#14050000
1!
#14100000
0!
0"
#14150000
1!
#14200000
0!
0"
#14250000
1!
#14300000
0!
0"
#14350000
1!
#14400000
0!
0"
#14450000
1!
#14500000
0!
0"
#14550000
1!
#14600000
1*
b1 -
b1 /
0!
1"
#14650000
0*
b0 -
b0 /
1,
b1 .
b1 0
1!
#14700000
1)
b10 -
b10 /
0!
0"
#14750000
0)
b0 /
b0 -
b10 0
b10 .
0,
1+
1!
#14800000
0!
0"
#14850000
0+
b0 .
b0 0
1!
#14900000
1*
b1 -
b1 /
0!
1"
#14950000
0*
b0 /
b0 -
b1 0
b1 .
1,
1!
#15000000
1)
b10 -
b10 /
0!
0"
#15050000
0)
b0 -
b0 /
1+
0,
b10 .
b10 0
1!
#15100000
0!
0"
#15150000
b0 0
b0 .
0+
1!
#15200000
0!
0"
#15250000
1!
#15300000
0!
0"
#15350000
1!
#15400000
0!
0"
#15450000
1!
#15500000
0!
0"
#15550000
1!
#15600000
0!
0"
#15650000
1!
#15700000
0!
0"
#15750000
1!
#15800000
0!
0"
#15850000
1!
#15900000
0!
0"
#15950000
1!
#16000000
0!
0"
#16050000
1!
#16100000
1*
b1 -
b1 /
0!
1"
#16150000
0*
b0 /
b0 -
b1 0
b1 .
1,
1!
#16200000
1)
b10 -
b10 /
0!
0"
#16250000
0)
b0 -
b0 /
1+
0,
b10 .
b10 0
1!
#16300000
1)
1(
1*
1'
b11 -
b11 /
0!
1"
#16350000
0)
0(
0*
1&
b0 /
b0 -
0'
b11 0
b11 .
1%
1,
1$
1!
#16400000
1)
b10 -
b10 /
0!
0"
#16450000
0)
b0 -
0&
b0 /
0$
0,
0%
b10 .
b10 0
1!
#16500000
0!
0"
#16550000
b0 0
b0 .
0+
1!
#16600000
0!
0"
#16650000
1!
#16700000
0!
0"
#16750000
1!
#16800000
0!
0"
#16850000
1!
#16900000
0!
0"
#16950000
1!
#17000000
0!
0"
#17050000
1!
#17100000
0!
0"
#17150000
1!
#17200000
0!
0"
#17250000
1!
#17300000
0!
0"
#17350000
1!
#17400000
1*
b1 -
b1 /
0!
1"
#17450000
0*
b0 -
b0 /
1,
b1 .
b1 0
1!
#17500000
0!
1"
#17550000
1*
b1 /
b1 -
b0 0
b0 .
0,
1!
#17600000
0*
b0 -
b0 /
0!
0"
#17650000
1!
#17700000
1*
b1 -
b1 /
0!
1"
#17750000
0*
b0 /
b0 -
b1 0
b1 .
1,
1!
#17800000
1)
b10 -
b10 /
0!
0"
#17850000
0)
b0 -
b0 /
1+
0,
b10 .
b10 0
1!
#17900000
0!
0"
#17950000
b0 0
b0 .
0+
1!
#18000000
0!
0"
#18050000
1!
#18100000
0!
0"
#18150000
1!
#18200000
0!
0"
#18250000
1!
#18300000
0!
0"
#18350000
1!
#18400000
0!
0"
#18450000
1!
#18500000
0!
0"
#18550000
1!
#18600000
0!
0"
#18650000
1!
#18700000
0!
0"
#18750000
1!
#18800000
0!
0"
#18850000
1!
#18900000
0!
0"
#18950000
1!
#19000000
1*
b1 -
b1 /
0!
1"
#19050000
0*
b0 -
b0 /
1,
b1 .
b1 0
1!
#19100000
0!
1"
#19150000
1*
b1 /
b1 -
b0 0
b0 .
0,
1!
#19200000
0*
b0 -
b0 /
0!
0"
#19250000
1!
#19300000
0!
0"
#19350000
1!
#19400000
0!
0"
#19450000
1!
#19500000
0!
0"
#19550000
1!
#19600000
0!
0"
#19650000
1!
#19700000
0!
0"
#19750000
1!
#19800000
0!
0"
#19850000
1!
#19900000
0!
0"
#19950000
1!
#20000000
0!
0"
#20050000
1!
#20100000
0!
0"
#20150000
1!
#20200000
1*
b1 -
b1 /
0!
1"
#20250000
0*
b0 -
b0 /
1,
b1 .
b1 0
1!
#20300000
1)
b10 -
b10 /
0!
0"
#20350000
0)
b0 /
b0 -
b10 0
b10 .
0,
1+
1!
#20400000
1)
1(
1*
1'
b11 -
b11 /
0!
1"
#20450000
0)
0(
0*
b0 -
0'
1&
b0 /
1$
1,
1%
b11 .
b11 0
1!
#20500000
0!
1"
#20550000
1*
0&
b1 /
b1 -
b0 0
b0 .
0%
0,
0+
0$
1!
#20600000
0*
b0 -
b0 /
0!
0"
#20650000
1!
#20700000
0!
0"
#20750000
1!
#20800000
0!
0"
#20850000
1!
#20900000
0!
0"
#20950000
1!
#21000000
0!
0"
#21050000
1!
#21100000
0!
0"
#21150000
1!
#21200000
0!
0"
#21250000
1!
#21300000
0!
0"
#21350000
1!
#21400000
0!
0"
#21450000
1!
#21500000
0!
0"
#21550000
1!
#21600000
0!
0"
#21650000
1!
#21700000
1*
b1 -
b1 /
0!
1"
#21750000
0*
b0 /
b0 -
b1 0
b1 .
1,
1!
#21800000
0!
1"
#21850000
1*
b1 -
b1 /
0,
b0 .
b0 0
1!
#21900000
0!
1"
#21950000
0*
b0 /
b0 -
b1 0
b1 .
1,
1!
#22000000
1)
b10 -
b10 /
0!
0"
#22050000
0)
b0 -
b0 /
1+
0,
b10 .
b10 0
1!
#22100000
0!
0"
#22150000
b0 0
b0 .
0+
1!
#22200000
0!
0"
#22250000
1!
#22300000
0!
0"
#22350000
1!
#22400000
0!
0"
#22450000
1!
#22500000
0!
0"
#22550000
1!
#22600000
0!
0"
#22650000
1!
#22700000
0!
0"
#22750000
1!
#22800000
0!
0"
#22850000
1!
#22900000
0!
0"
#22950000
1!
#23000000
1*
b1 -
b1 /
0!
1"
#23050000
0*
b0 -
b0 /
1,
b1 .
b1 0
1!
#23100000
0!
1"
#23150000
1*
b1 /
b1 -
b0 0
b0 .
0,
1!
#23200000
0!
1"
#23250000
0*
b0 -
b0 /
1,
b1 .
b1 0
1!
#23300000
0!
1"
#23350000
1*
b1 /
b1 -
b0 0
b0 .
0,
1!
#23400000
0*
b0 -
b0 /
0!
0"
#23450000
1!
#23500000
0!
0"
#23550000
1!
#23600000
0!
0"
#23650000
1!
#23700000
0!
0"
#23750000
1!
#23800000
0!
0"
#23850000
1!
#23900000
0!
0"
#23950000
1!
#24000000
0!
0"
#24050000
1!
#24100000
0!
0"
#24150000
1!
#24200000
0!
0"
#24250000
1!
#24300000
0!
0"
#24350000
1!
#24400000
0!
0"
#24450000
1!
#24500000
0!
0"
#24550000
1!
#24600000
0!
0"
#24650000
1!
#24700000
0!
0"
#24750000
1!
#24800000
1*
b1 -
b1 /
0!
1"
#24850000
0*
b0 -
b0 /
1,
b1 .
b1 0
1!
#24900000
1)
b10 -
b10 /
0!
0"
#24950000
0)
b0 /
b0 -
b10 0
b10 .
0,
1+
1!
#25000000
0!
0"
#25050000
0+
b0 .
b0 0
1!
#25100000
0!
0"
#25150000
1!
#25200000
0!
0"
#25250000
1!
#25300000
0!
0"
#25350000
1!
#25400000
0!
0"
#25450000
1!
#25500000
0!
0"
#25550000
1!
#25600000
0!
0"
#25650000
1!
#25700000
0!
0"
#25750000
1!
#25800000
1*
b1 -
b1 /
0!
1"
#25850000
0*
b0 -
b0 /
1,
b1 .
b1 0
1!
#25900000
1)
b10 -
b10 /
0!
0"
#25950000
0)
b0 /
b0 -
b10 0
b10 .
0,
1+
1!
#26000000
0!
0"
#26050000
0+
b0 .
b0 0
1!
#26100000
0!
0"
#26150000
1!
#26200000
1*
b1 -
b1 /
0!
1"
#26250000
0*
b0 -
b0 /
1,
b1 .
b1 0
1!
#26300000
1)
b10 -
b10 /
0!
0"
#26350000
0)
b0 /
b0 -
b10 0
b10 .
0,
1+
1!
#26400000
0!
0"
#26450000
0+
b0 .
b0 0
1!
#26500000
0!
0"
#26550000
1!
#26600000
0!
0"
#26650000
1!
#26700000
0!
0"
#26750000
1!
#26800000
0!
0"
#26850000
1!
#26900000
0!
0"
#26950000
1!
#27000000
0!
0"
#27050000
1!
#27100000
0!
0"
#27150000
1!
#27200000
0!
0"
#27250000
1!
#27300000
1*
b1 -
b1 /
0!
1"
#27350000
0*
b0 /
b0 -
b1 0
b1 .
1,
1!
#27400000
1)
b10 -
b10 /
0!
0"
#27450000
0)
b0 -
b0 /
1+
0,
b10 .
b10 0
1!
#27500000
0!
0"
#27550000
b0 0
b0 .
0+
1!
#27600000
1*
b1 -
b1 /
0!
1"
#27650000
0*
b0 -
b0 /
1,
b1 .
b1 0
1!
#27700000
1)
b10 -
b10 /
0!
0"
#27750000
0)
b0 /
b0 -
b10 0
b10 .
0,
1+
1!
#27800000
0!
0"
#27850000
0+
b0 .
b0 0
1!
#27900000
0!
0"
#27950000
1!
#28000000
0!
0"
#28050000
1!
#28100000
0!
0"
#28150000
1!
#28200000
0!
0"
#28250000
1!
#28300000
0!
0"
#28350000
1!
#28400000
0!
0"
#28450000
1!
#28500000
0!
0"
#28550000
1!
#28600000
1*
b1 -
b1 /
0!
1"
#28650000
0*
b0 -
b0 /
1,
b1 .
b1 0
1!
#28700000
0!
1"
#28750000
1*
b1 /
b1 -
b0 0
b0 .
0,
1!
#28800000
0*
b0 -
b0 /
0!
0"
#28850000
1!
#28900000
0!
0"
#28950000
1!
#29000000
1*
b1 -
b1 /
0!
1"
#29050000
0*
b0 -
b0 /
1,
b1 .
b1 0
1!
#29100000
1)
b10 -
b10 /
0!
0"
#29150000
0)
b0 /
b0 -
b10 0
b10 .
0,
1+
1!
#29200000
0!
0"
#29250000
0+
b0 .
b0 0
1!
#29300000
0!
0"
#29350000
1!
#29400000
0!
0"
#29450000
1!
#29500000
0!
0"
#29550000
1!
#29600000
0!
0"
#29650000
1!
#29700000
0!
0"
#29750000
1!
#29800000
0!
0"
#29850000
1!
#29900000
0!
0"
#29950000
1!
#30000000
0!
0"
#30050000
1!
#30100000
0!
0"
#30150000
1!
#30200000
1*
b1 -
b1 /
0!
1"
#30250000
0*
b0 -
b0 /
1,
b1 .
b1 0
1!
#30300000
1)
b10 -
b10 /
0!
0"
#30350000
0)
b0 /
b0 -
b10 0
b10 .
0,
1+
1!
#30400000
1)
1(
1*
b11 -
1'
b11 /
0!
1"
#30450000
0)
0(
0*
0'
b0 -
1&
b0 /
1$
1,
1%
b11 .
b11 0
1!
#30500000
1)
b10 -
b10 /
0!
0"
#30550000
0)
0&
b0 /
b0 -
b10 0
b10 .
0%
0,
0$
1!
#30600000
0!
0"
#30650000
0+
b0 .
b0 0
1!
#30700000
0!
0"
#30750000
1!
#30800000
0!
0"
#30850000
1!
#30900000
0!
0"
#30950000
1!
#31000000
0!
0"
#31050000
1!
#31100000
0!
0"
#31150000
1!
#31200000
0!
0"
#31250000
1!
#31300000
0!
0"
#31350000
1!
#31400000
1*
b1 -
b1 /
0!
1"
#31450000
0*
b0 -
b0 /
1,
b1 .
b1 0
1!
#31500000
1)
b10 -
b10 /
0!
0"
#31550000
0)
b0 /
b0 -
b10 0
b10 .
0,
1+
1!
#31600000
1)
1(
1*
1'
b11 -
b11 /
0!
1"
#31650000
0)
0(
0*
b0 -
0'
1&
b0 /
1$
1,
1%
b11 .
b11 0
1!
#31700000
1)
b10 -
b10 /
0!
0"
#31750000
0)
0&
b0 /
b0 -
b10 0
b10 .
0%
0,
0$
1!
#31800000
1)
1(
1*
1'
b11 -
b11 /
0!
1"
#31850000
0)
0(
0*
b0 -
0'
1&
b0 /
1$
1,
1%
b11 .
b11 0
1!
#31900000
1)
b10 -
b10 /
0!
0"
#31950000
0)
0&
b0 /
b0 -
b10 0
b10 .
0%
0,
0$
1!
#32000000
0!
0"
#32050000
0+
b0 .
b0 0
1!
#32100000
0!
0"
#32150000
1!
#32200000
0!
0"
#32250000
1!
#32300000
0!
0"
#32350000
1!
#32400000
0!
0"
#32450000
1!
#32500000
0!
0"
#32550000
1!
#32600000
0!
0"
#32650000
1!
#32700000
0!
0"
#32750000
1!
#32800000
0!
0"
#32850000
1!
#32900000
1*
b1 -
b1 /
0!
1"
#32950000
0*
b0 /
b0 -
b1 0
b1 .
1,
1!
#33000000
0!
1"
#33050000
1*
b1 -
b1 /
0,
b0 .
b0 0
1!
#33100000
0*
b0 -
b0 /
0!
0"
#33150000
1!
#33200000
1*
b1 -
b1 /
0!
1"
#33250000
0*
b0 -
b0 /
1,
b1 .
b1 0
1!
#33300000
1)
b10 -
b10 /
0!
0"
#33350000
0)
b0 /
b0 -
b10 0
b10 .
0,
1+
1!
#33400000
0!
0"
#33450000
0+
b0 .
b0 0
1!
#33500000
0!
0"
#33550000
1!
#33600000
0!
0"
#33650000
1!
#33700000
0!
0"
#33750000
1!
#33800000
0!
0"
#33850000
1!
#33900000
0!
0"
#33950000
1!
#34000000
0!
0"
#34050000
1!
#34100000
0!
0"
#34150000
1!
#34200000
1*
b1 -
b1 /
0!
1"
#34250000
0*
b0 -
b0 /
1,
b1 .
b1 0
1!
#34300000
0!
1"
#34350000
1*
b1 /
b1 -
b0 0
b0 .
0,
1!
#34400000
0!
1"
#34450000
0*
b0 -
b0 /
1,
b1 .
b1 0
1!
#34500000
1)
b10 -
b10 /
0!
0"
#34550000
0)
b0 /
b0 -
b10 0
b10 .
0,
1+
1!
#34600000
1)
1(
1*
1'
b11 -
b11 /
0!
1"
#34650000
0)
0(
0*
b0 -
0'
1&
b0 /
1$
1,
1%
b11 .
b11 0
1!
#34700000
1)
b10 -
b10 /
0!
0"
#34750000
0)
0&
b0 /
b0 -
b10 0
b10 .
0%
0,
0$
1!
#34800000
0!
0"
#34850000
0+
b0 .
b0 0
1!
#34900000
0!
0"
#34950000
1!
#35000000
0!
0"
#35050000
1!
#35100000
0!
0"
#35150000
1!
#35200000
0!
0"
#35250000
1!
#35300000
0!
0"
#35350000
1!
#35400000
0!
0"
#35450000
1!
#35500000
0!
0"
#35550000
1!
#35600000
0!
0"
#35650000
1!
#35700000
0!
0"
#35750000
1!
#35800000
0!
0"
#35850000
1!
#35900000
1*
b1 -
b1 /
0!
1"
#35950000
0*
b0 /
b0 -
b1 0
b1 .
1,
1!
#36000000
0!
1"
#36050000
1*
b1 -
b1 /
0,
b0 .
b0 0
1!
#36100000
0*
b0 -
b0 /
0!
0"
#36150000
1!
#36200000
0!
0"
#36250000
1!
#36300000
0!
0"
#36350000
1!
#36400000
0!
0"
#36450000
1!
#36500000
0!
0"
#36550000
1!
#36600000
0!
0"
#36650000
1!
#36700000
0!
0"
#36750000
1!
#36800000
0!
0"
#36850000
1!
#36900000
0!
0"
#36950000
1!
#37000000
1*
b1 -
b1 /
0!
1"
#37050000
0*
b0 -
b0 /
1,
b1 .
b1 0
1!
#37100000
1)
b10 -
b10 /
0!
0"
#37150000
0)
b0 /
b0 -
b10 0
b10 .
0,
1+
1!
#37200000
0!
0"
#37250000
0+
b0 .
b0 0
1!
#37300000
1*
b1 -
b1 /
0!
1"
#37350000
0*
b0 /
b0 -
b1 0
b1 .
1,
1!
#37400000
0!
1"
#37450000
1*
b1 -
b1 /
0,
b0 .
b0 0
1!
#37500000
0*
b0 -
b0 /
0!
0"
#37550000
1!
#37600000
0!
0"
#37650000
1!
#37700000
0!
0"
#37750000
1!
#37800000
0!
0"
#37850000
1!
#37900000
0!
0"
#37950000
1!
#38000000
0!
0"
#38050000
1!
#38100000
0!
0"
#38150000
1!
#38200000
0!
0"
#38250000
1!
#38300000
0!
0"
#38350000
1!
#38400000
0!
0"
#38450000
1!
#38500000
1*
b1 -
b1 /
0!
1"
#38550000
0*
b0 /
b0 -
b1 0
b1 .
1,
1!
#38600000
1)
b10 -
b10 /
0!
0"
#38650000
0)
b0 -
b0 /
1+
0,
b10 .
b10 0
1!
#38700000
1)
1(
1*
1'
b11 -
b11 /
0!
1"
#38750000
0)
0(
0*
1&
b0 /
b0 -
0'
b11 0
b11 .
1%
1,
1$
1!
#38800000
0!
1"
